akamaichinaCDN/__init__.py
akamaichinaCDN/akamaichinaCDN.py
akamaichinaCDN/application_type.json
akamaichinaCDN/http_calls.py
akamaichinaCDN/legaltype.json
akamaichinaCDN-0.1.data/data/akamaichinaCDN/application_type.json
akamaichinaCDN-0.1.data/data/akamaichinaCDN/legaltype.json
akamaichinaCDN-0.1.dist-info/LICENSE
akamaichinaCDN-0.1.dist-info/METADATA
akamaichinaCDN-0.1.dist-info/WHEEL
akamaichinaCDN-0.1.dist-info/top_level.txt
akamaichinaCDN-0.1.dist-info/RECORD
