Metadata-Version: 2.1
Name: akamaichinaCDN
Version: 0.1
Summary: A Pip Package for Akamai China CDN
Home-page: https://github.com/Achuthananda/AkamaiChinaCDN
Author: Achuthananda M P
Author-email: achuthadivine@gmail.com
License: UNKNOWN
Platform: UNKNOWN
Classifier: Programming Language :: Python :: 3
Classifier: License :: OSI Approved :: MIT License
Classifier: Operating System :: OS Independent
